error_suggester/__init__.py
error_suggester/error_suggester.py
error_suggester-0.1.3.dist-info/LICENSE
error_suggester-0.1.3.dist-info/METADATA
error_suggester-0.1.3.dist-info/WHEEL
error_suggester-0.1.3.dist-info/top_level.txt
error_suggester-0.1.3.dist-info/RECORD
