Metadata-Version: 2.1
Name: error-suggester
Version: 0.1.3
Summary: A Python library for error suggestions using ChatGPT
Home-page: https://github.com/HarisBinSaif/ErrorSuggester
Author: HarisBinSaif
Project-URL: GitHub, https://github.com/HarisBinSaif/ErrorSuggester
License-File: LICENSE
Requires-Dist: openai
